pkpass/__init__.py
pkpass-0.1.1.dist-info/METADATA
pkpass-0.1.1.dist-info/WHEEL
pkpass-0.1.1.dist-info/top_level.txt
pkpass-0.1.1.dist-info/RECORD
