Metadata-Version: 2.1
Name: pkpass
Version: 0.1.1
Summary: General-purpose .pkpass file reader, includes airline and train specific parsers
Home-page: http://github.com/konradit/pkpass
Author: Konrad Iturbe
Author-email: mail@chernowii.com
License: MIT
Platform: UNKNOWN
